pumpfunpy/__init__.py
pumpfunpy/api.py
pumpfunpy/config.py
pumpfunpy/exceptions.py
pumpfunpy/streamers.py
pumpfunpy/transport.py
pumpfunpy/utils.py
pumpfunpy/endpoints/__init__.py
pumpfunpy/endpoints/advanced.py
pumpfunpy/endpoints/dexscreener.py
pumpfunpy/endpoints/frontend.py
pumpfunpy/endpoints/swap.py
pumpfunpy-0.1.2.dist-info/METADATA
pumpfunpy-0.1.2.dist-info/WHEEL
pumpfunpy-0.1.2.dist-info/top_level.txt
pumpfunpy-0.1.2.dist-info/RECORD
