Metadata-Version: 2.4
Name: pumpfunpy
Version: 0.1.2
Summary: The Bloomberg Terminal for Degenerates
Author-email: Tan Ping Zhi <pumpfunpy@gmail.com>
Project-URL: Source, https://github.com/TanPingZhi/pumpfunpy
Keywords: solana,pumpfun,trading,api,async
Classifier: Programming Language :: Python :: 3
Classifier: License :: OSI Approved :: MIT License
Classifier: Operating System :: OS Independent
Requires-Python: >=3.8
Requires-Dist: requests<3.0,>=2.31.0
Requires-Dist: python-socketio<6.0,>=5.0
Requires-Dist: websockets<16.0,>=15.0
Requires-Dist: aiohttp<4.0,>=3.8
